passagemath_macaulay2-10.5.40.dist-info/RECORD
passagemath_macaulay2-10.5.40.dist-info/WHEEL
passagemath_macaulay2-10.5.40.dist-info/top_level.txt
passagemath_macaulay2-10.5.40.dist-info/METADATA
sage/all__sagemath_macaulay2.py
sage/libs/macaulay2.cpython-39-darwin.so
sage/libs/all__sagemath_macaulay2.py
sage/interfaces/macaulay2.py
sage/interfaces/all__sagemath_macaulay2.py
