Metadata-Version: 2.4
Name: passagemath-macaulay2
Version: 10.5.40
Summary: passagemath: Computing in commutative algebra, algebraic geometry and related fields with Macaulay2
Author-email: The Sage Developers <sage-support@googlegroups.com>
Maintainer: Matthias Köppe, passagemath contributors
License-Expression: GPL-2.0-or-later
Project-URL: release notes, https://github.com/passagemath/passagemath/releases
Project-URL: repo (upstream), https://github.com/sagemath/sage
Project-URL: repo, https://github.com/passagemath/passagemath
Project-URL: documentation, https://doc.sagemath.org
Project-URL: homepage (upstream), https://www.sagemath.org
Project-URL: discourse, https://passagemath.discourse.group
Project-URL: tracker (upstream), https://github.com/sagemath/sage/issues
Project-URL: tracker, https://github.com/passagemath/passagemath/issues
Classifier: Development Status :: 6 - Mature
Classifier: Intended Audience :: Education
Classifier: Intended Audience :: Science/Research
Classifier: Operating System :: POSIX
Classifier: Operating System :: MacOS :: MacOS X
Classifier: Programming Language :: Python :: 3 :: Only
Classifier: Programming Language :: Python :: 3.9
Classifier: Programming Language :: Python :: 3.10
Classifier: Programming Language :: Python :: 3.11
Classifier: Programming Language :: Python :: 3.12
Classifier: Programming Language :: Python :: 3.13
Classifier: Programming Language :: Python :: Implementation :: CPython
Classifier: Topic :: Scientific/Engineering :: Mathematics
Requires-Python: <3.14,>=3.9
Requires-Dist: cysignals==1.12.0rc2
Requires-Dist: passagemath-categories~=10.5.40.0
Requires-Dist: passagemath-flint~=10.5.40.0
Requires-Dist: passagemath-modules~=10.5.40.0
Requires-Dist: passagemath-repl~=10.5.40.0
Provides-Extra: test
Requires-Dist: passagemath-linbox; extra == "test"
